Workbook

Sheet Executive Summary
A1: Executive Summary
A2: Green rows = facts already captured on 2026-10-12. Formulas count the manual observation tabs.
A4: Item | B4: Value | C4: Kind | D4: Source | E4: Observed
A5: Target | B5: Plazza (plazza.in), PLAZZA HEALTH PRIVATE LIMITED | C5: observed | D5: https://plazza.in (schema.org JSON-LD in page HTML) | E5: 2026-10-12
A6: Registered/office address | B6: 5th Floor, Tower A, No. 51, Innov8 Mantri Commercio, Bellandur, Bengaluru 560103 | C6: claimed | D6: https://plazza.in (schema.org JSON-LD in page HTML) | E6: 2026-10-12
A7: Service area | B7: Bengaluru only (structured data and FAQ) | C7: claimed | D7: https://plazza.in (schema.org JSON-LD in page HTML) | E7: 2026-10-12
A8: Delivery promise | B8: 15 minutes; handling 5–15 min stated in Offer data | C8: claimed | D8: https://plazza.in (schema.org JSON-LD in page HTML) | E8: 2026-10-12
A9: Hours | B9: 24/7 (00:00–23:59 every day) | C9: claimed | D9: https://plazza.in (schema.org JSON-LD in page HTML) | E9: 2026-10-12
A10: Assortment claim | B10: Inconsistent: 20,000+ / 35,000+ / 100,000+ in different blocks | C10: claimed | D10: https://plazza.in (schema.org JSON-LD in page HTML) | E10: 2026-10-12
A11: Minimum order value | B11: None ("no minimum order value", FAQ) | C11: claimed | D11: https://plazza.in (schema.org JSON-LD in page HTML) | E11: 2026-10-12
A12: Shipping rate in Offer data | B12: ₹0 | C12: claimed | D12: https://plazza.in (schema.org JSON-LD in page HTML) | E12: 2026-10-12
A13: Payment methods | B13: COD, cards, UPI, net banking, wallets (FAQ) | C13: claimed | D13: https://plazza.in (schema.org JSON-LD in page HTML) | E13: 2026-10-12
A14: App rating (from their page) | B14: 4.1 from 31 ratings; not verified against the stores | C14: claimed | D14: https://plazza.in (schema.org JSON-LD in page HTML) | E14: 2026-10-12
A15: Automated catalogue collection | B15: Not performed: product data loads only from /api/, which robots.txt disallows | C15: observed | D15: https://plazza.in/robots.txt | E15: 2026-10-12
A16: SKUs observed (manual) | B16: =COUNTA('Master SKU Catalogue'!D5:D5000) | C16: calculated | D16: Master SKU Catalogue
A17: SKUs with selling price (manual) | B17: =COUNT('Master SKU Catalogue'!P5:P5000) | C17: calculated | D17: Master SKU Catalogue
A18: Observed availability % (of SKUs with status) | B18: =IFERROR(ROUND(100*COUNTIF('Master SKU Catalogue'!R5:R5000,"in_stock")/(COUNTIF('Master SKU Catalogue'!R5:R5000,"in_stock")+COUNTIF('Master SKU Catalogue'!R5:R5000,"out_of_stock")),1),"n/a") | C18: calculated | D18: Master SKU Catalogue
A19: Median discount % (manual) | B19: =IFERROR(MEDIAN('Master SKU Catalogue'!Q5:Q5000),"n/a") | C19: calculated | D19: Master SKU Catalogue
A20: Basket scenarios recorded | B20: =COUNT('Basket Experiments'!L5:L100) | C20: calculated | D20: Basket Experiments
A21: ETA rows (incl. claims) | B21: =COUNTA('Delivery ETA'!E5:E2000) | C21: calculated | D21: Delivery ETA
A22: Search queries tested | B22: =COUNT('Search Tests'!C5:C200) | C22: calculated | D22: Search Tests

Sheet Category Tree
A1: Category Tree
A2: One row per category/subcategory seen in the app or website navigation.
A4: Category ID (if shown) | B4: Category | C4: Parent | D4: Display order | E4: URL / screen | F4: Products seen | G4: Available | H4: Unavailable | I4: Category offer | J4: Delivery promise shown | K4: Badges | L4: Observed at | M4: Screenshot | N4: Notes
B5: Prescription Medicines; OTC; Vitamins & Supplements; Baby Care; Personal Care | E5: homepage structured data | L5: 2026-10-12 | N5: Claimed in schema.org ItemList, not navigation
B6: Fever; Cold & Cough; Diabetes; Blood Pressure; Antibiotics; Vitamins | E6: homepage structured data | L6: 2026-10-12 | N6: Claimed "popular categories" list

Sheet Master SKU Catalogue
A1: Master SKU Catalogue
A2: Record products as an ordinary customer sees them at the fixed address. Keep each pack size as its own row. Leave unknowns blank; never guess.
A4: Obs ID | B4: Observed at (IST) | C4: Address PIN | D4: Product name (as shown) | E4: Product URL / screen | F4: Product ID (if in URL) | G4: Brand | H4: Manufacturer | I4: Composition | J4: Strength | K4: Dosage form | L4: Pack size | M4: Rx required (shown) | N4: Category | O4: MRP ₹ | P4: Selling price ₹ | Q4: Discount % | R4: Availability | S4: Add-to-cart enabled | T4: ETA text (exact) | U4: Max qty shown | V4: Substitutes shown | W4: Screenshot | X4: Notes
Q5: =IF(AND(ISNUMBER(O5),ISNUMBER(P5),O5>0),ROUND((O5-P5)/O5*100,1),"")
Q6: =IF(AND(ISNUMBER(O6),ISNUMBER(P6),O6>0),ROUND((O6-P6)/O6*100,1),"")
Q7: =IF(AND(ISNUMBER(O7),ISNUMBER(P7),O7>0),ROUND((O7-P7)/O7*100,1),"")
Q8: =IF(AND(ISNUMBER(O8),ISNUMBER(P8),O8>0),ROUND((O8-P8)/O8*100,1),"")
Q9: =IF(AND(ISNUMBER(O9),ISNUMBER(P9),O9>0),ROUND((O9-P9)/O9*100,1),"")
Q10: =IF(AND(ISNUMBER(O10),ISNUMBER(P10),O10>0),ROUND((O10-P10)/O10*100,1),"")
Q11: =IF(AND(ISNUMBER(O11),ISNUMBER(P11),O11>0),ROUND((O11-P11)/O11*100,1),"")
Q12: =IF(AND(ISNUMBER(O12),ISNUMBER(P12),O12>0),ROUND((O12-P12)/O12*100,1),"")
Q13: =IF(AND(ISNUMBER(O13),ISNUMBER(P13),O13>0),ROUND((O13-P13)/O13*100,1),"")
Q14: =IF(AND(ISNUMBER(O14),ISNUMBER(P14),O14>0),ROUND((O14-P14)/O14*100,1),"")
Q15: =IF(AND(ISNUMBER(O15),ISNUMBER(P15),O15>0),ROUND((O15-P15)/O15*100,1),"")
Q16: =IF(AND(ISNUMBER(O16),ISNUMBER(P16),O16>0),ROUND((O16-P16)/O16*100,1),"")
... Q2000: =IF(AND(ISNUMBER(O2000),ISNUMBER(P2000),O2000>0),ROUND((O2000-P2000)/O2000*100,1),"")

Sheet SKU Availability
A1: SKU Availability
A2: Calculated from Master SKU Catalogue (column N must use these category names).
A4: Category | B4: SKUs observed | C4: In stock | D4: Out of stock | E4: Unknown | F4: Observed availability % | G4: Note
A5: Prescription medicines | B5: =COUNTIF('Master SKU Catalogue'!$N$5:$N$5000,A5) | C5: =COUNTIFS('Master SKU Catalogue'!$N$5:$N$5000,A5,'Master SKU Catalogue'!$R$5:$R$5000,"in_stock") | D5: =COUNTIFS('Master SKU Catalogue'!$N$5:$N$5000,A5,'Master SKU Catalogue'!$R$5:$R$5000,"out_of_stock") | E5: =COUNTIFS('Master SKU Catalogue'!$N$5:$N$5000,A5,'Master SKU Catalogue'!$R$5:$R$5000,"unknown") | F5: =IFERROR(ROUND(C5/(C5+D5)*100,1),"n/a") | G5: Denominator excludes unknown status
A6: OTC medicines | B6: =COUNTIF('Master SKU Catalogue'!$N$5:$N$5000,A6) | C6: =COUNTIFS('Master SKU Catalogue'!$N$5:$N$5000,A6,'Master SKU Catalogue'!$R$5:$R$5000,"in_stock") | D6: =COUNTIFS('Master SKU Catalogue'!$N$5:$N$5000,A6,'Master SKU Catalogue'!$R$5:$R$5000,"out_of_stock") | E6: =COUNTIFS('Master SKU Catalogue'!$N$5:$N$5000,A6,'Master SKU Catalogue'!$R$5:$R$5000,"unknown") | F6: =IFERROR(ROUND(C6/(C6+D6)*100,1),"n/a") | G6: Denominator excludes unknown status
A7: Vitamins & supplements | B7: =COUNTIF('Master SKU Catalogue'!$N$5:$N$5000,A7) | C7: =COUNTIFS('Master SKU Catalogue'!$N$5:$N$5000,A7,'Master SKU Catalogue'!$R$5:$R$5000,"in_stock") | D7: =COUNTIFS('Master SKU Catalogue'!$N$5:$N$5000,A7,'Master SKU Catalogue'!$R$5:$R$5000,"out_of_stock") | E7: =COUNTIFS('Master SKU Catalogue'!$N$5:$N$5000,A7,'Master SKU Catalogue'!$R$5:$R$5000,"unknown") | F7: =IFERROR(ROUND(C7/(C7+D7)*100,1),"n/a") | G7: Denominator excludes unknown status
A8: Personal care | B8: =COUNTIF('Master SKU Catalogue'!$N$5:$N$5000,A8) | C8: =COUNTIFS('Master SKU Catalogue'!$N$5:$N$5000,A8,'Master SKU Catalogue'!$R$5:$R$5000,"in_stock") | D8: =COUNTIFS('Master SKU Catalogue'!$N$5:$N$5000,A8,'Master SKU Catalogue'!$R$5:$R$5000,"out_of_stock") | E8: =COUNTIFS('Master SKU Catalogue'!$N$5:$N$5000,A8,'Master SKU Catalogue'!$R$5:$R$5000,"unknown") | F8: =IFERROR(ROUND(C8/(C8+D8)*100,1),"n/a") | G8: Denominator excludes unknown status
A9: Baby care | B9: =COUNTIF('Master SKU Catalogue'!$N$5:$N$5000,A9) | C9: =COUNTIFS('Master SKU Catalogue'!$N$5:$N$5000,A9,'Master SKU Catalogue'!$R$5:$R$5000,"in_stock") | D9: =COUNTIFS('Master SKU Catalogue'!$N$5:$N$5000,A9,'Master SKU Catalogue'!$R$5:$R$5000,"out_of_stock") | E9: =COUNTIFS('Master SKU Catalogue'!$N$5:$N$5000,A9,'Master SKU Catalogue'!$R$5:$R$5000,"unknown") | F9: =IFERROR(ROUND(C9/(C9+D9)*100,1),"n/a") | G9: Denominator excludes unknown status
A10: Diabetes care | B10: =COUNTIF('Master SKU Catalogue'!$N$5:$N$5000,A10) | C10: =COUNTIFS('Master SKU Catalogue'!$N$5:$N$5000,A10,'Master SKU Catalogue'!$R$5:$R$5000,"in_stock") | D10: =COUNTIFS('Master SKU Catalogue'!$N$5:$N$5000,A10,'Master SKU Catalogue'!$R$5:$R$5000,"out_of_stock") | E10: =COUNTIFS('Master SKU Catalogue'!$N$5:$N$5000,A10,'Master SKU Catalogue'!$R$5:$R$5000,"unknown") | F10: =IFERROR(ROUND(C10/(C10+D10)*100,1),"n/a") | G10: Denominator excludes unknown status
A11: Medical devices | B11: =COUNTIF('Master SKU Catalogue'!$N$5:$N$5000,A11) | C11: =COUNTIFS('Master SKU Catalogue'!$N$5:$N$5000,A11,'Master SKU Catalogue'!$R$5:$R$5000,"in_stock") | D11: =COUNTIFS('Master SKU Catalogue'!$N$5:$N$5000,A11,'Master SKU Catalogue'!$R$5:$R$5000,"out_of_stock") | E11: =COUNTIFS('Master SKU Catalogue'!$N$5:$N$5000,A11,'Master SKU Catalogue'!$R$5:$R$5000,"unknown") | F11: =IFERROR(ROUND(C11/(C11+D11)*100,1),"n/a") | G11: Denominator excludes unknown status
A12: Ayurveda | B12: =COUNTIF('Master SKU Catalogue'!$N$5:$N$5000,A12) | C12: =COUNTIFS('Master SKU Catalogue'!$N$5:$N$5000,A12,'Master SKU Catalogue'!$R$5:$R$5000,"in_stock") | D12: =COUNTIFS('Master SKU Catalogue'!$N$5:$N$5000,A12,'Master SKU Catalogue'!$R$5:$R$5000,"out_of_stock") | E12: =COUNTIFS('Master SKU Catalogue'!$N$5:$N$5000,A12,'Master SKU Catalogue'!$R$5:$R$5000,"unknown") | F12: =IFERROR(ROUND(C12/(C12+D12)*100,1),"n/a") | G12: Denominator excludes unknown status
A13: Other | B13: =COUNTIF('Master SKU Catalogue'!$N$5:$N$5000,A13) | C13: =COUNTIFS('Master SKU Catalogue'!$N$5:$N$5000,A13,'Master SKU Catalogue'!$R$5:$R$5000,"in_stock") | D13: =COUNTIFS('Master SKU Catalogue'!$N$5:$N$5000,A13,'Master SKU Catalogue'!$R$5:$R$5000,"out_of_stock") | E13: =COUNTIFS('Master SKU Catalogue'!$N$5:$N$5000,A13,'Master SKU Catalogue'!$R$5:$R$5000,"unknown") | F13: =IFERROR(ROUND(C13/(C13+D13)*100,1),"n/a") | G13: Denominator excludes unknown status

Sheet Medicine Details
A1: Medicine Details
A2: Only what the product page shows. Do not infer equivalence between brands.
A4: Obs ID (from catalogue) | B4: Product name | C4: Salt composition | D4: Therapeutic class (shown) | E4: Storage | F4: Warnings | G4: Expiry shown | H4: Batch shown | I4: Substitutes shown | J4: Alt strengths | K4: Alt pack sizes | L4: Screenshot

Sheet Pricing and Discounts
A1: Pricing and Discounts
A2: Calculated from Master SKU Catalogue.
A4: Category | B4: SKUs with MRP and price | C4: Average discount % | D4: Max discount % | E4: Selling > MRP (flag)
A5: Prescription medicines | B5: =COUNTIFS('Master SKU Catalogue'!$N$5:$N$5000,A5,'Master SKU Catalogue'!$Q$5:$Q$5000,">=-1000") | C5: =IFERROR(ROUND(AVERAGEIFS('Master SKU Catalogue'!$Q$5:$Q$5000,'Master SKU Catalogue'!$N$5:$N$5000,A5),1),"n/a") | D5: =IFERROR(_xlfn.MAXIFS('Master SKU Catalogue'!$Q$5:$Q$5000,'Master SKU Catalogue'!$N$5:$N$5000,A5),"n/a") | E5: =COUNTIFS('Master SKU Catalogue'!$N$5:$N$5000,A5,'Master SKU Catalogue'!$Q$5:$Q$5000,"<0")
A6: OTC medicines | B6: =COUNTIFS('Master SKU Catalogue'!$N$5:$N$5000,A6,'Master SKU Catalogue'!$Q$5:$Q$5000,">=-1000") | C6: =IFERROR(ROUND(AVERAGEIFS('Master SKU Catalogue'!$Q$5:$Q$5000,'Master SKU Catalogue'!$N$5:$N$5000,A6),1),"n/a") | D6: =IFERROR(_xlfn.MAXIFS('Master SKU Catalogue'!$Q$5:$Q$5000,'Master SKU Catalogue'!$N$5:$N$5000,A6),"n/a") | E6: =COUNTIFS('Master SKU Catalogue'!$N$5:$N$5000,A6,'Master SKU Catalogue'!$Q$5:$Q$5000,"<0")
A7: Vitamins & supplements | B7: =COUNTIFS('Master SKU Catalogue'!$N$5:$N$5000,A7,'Master SKU Catalogue'!$Q$5:$Q$5000,">=-1000") | C7: =IFERROR(ROUND(AVERAGEIFS('Master SKU Catalogue'!$Q$5:$Q$5000,'Master SKU Catalogue'!$N$5:$N$5000,A7),1),"n/a") | D7: =IFERROR(_xlfn.MAXIFS('Master SKU Catalogue'!$Q$5:$Q$5000,'Master SKU Catalogue'!$N$5:$N$5000,A7),"n/a") | E7: =COUNTIFS('Master SKU Catalogue'!$N$5:$N$5000,A7,'Master SKU Catalogue'!$Q$5:$Q$5000,"<0")
A8: Personal care | B8: =COUNTIFS('Master SKU Catalogue'!$N$5:$N$5000,A8,'Master SKU Catalogue'!$Q$5:$Q$5000,">=-1000") | C8: =IFERROR(ROUND(AVERAGEIFS('Master SKU Catalogue'!$Q$5:$Q$5000,'Master SKU Catalogue'!$N$5:$N$5000,A8),1),"n/a") | D8: =IFERROR(_xlfn.MAXIFS('Master SKU Catalogue'!$Q$5:$Q$5000,'Master SKU Catalogue'!$N$5:$N$5000,A8),"n/a") | E8: =COUNTIFS('Master SKU Catalogue'!$N$5:$N$5000,A8,'Master SKU Catalogue'!$Q$5:$Q$5000,"<0")
A9: Baby care | B9: =COUNTIFS('Master SKU Catalogue'!$N$5:$N$5000,A9,'Master SKU Catalogue'!$Q$5:$Q$5000,">=-1000") | C9: =IFERROR(ROUND(AVERAGEIFS('Master SKU Catalogue'!$Q$5:$Q$5000,'Master SKU Catalogue'!$N$5:$N$5000,A9),1),"n/a") | D9: =IFERROR(_xlfn.MAXIFS('Master SKU Catalogue'!$Q$5:$Q$5000,'Master SKU Catalogue'!$N$5:$N$5000,A9),"n/a") | E9: =COUNTIFS('Master SKU Catalogue'!$N$5:$N$5000,A9,'Master SKU Catalogue'!$Q$5:$Q$5000,"<0")
A10: Diabetes care | B10: =COUNTIFS('Master SKU Catalogue'!$N$5:$N$5000,A10,'Master SKU Catalogue'!$Q$5:$Q$5000,">=-1000") | C10: =IFERROR(ROUND(AVERAGEIFS('Master SKU Catalogue'!$Q$5:$Q$5000,'Master SKU Catalogue'!$N$5:$N$5000,A10),1),"n/a") | D10: =IFERROR(_xlfn.MAXIFS('Master SKU Catalogue'!$Q$5:$Q$5000,'Master SKU Catalogue'!$N$5:$N$5000,A10),"n/a") | E10: =COUNTIFS('Master SKU Catalogue'!$N$5:$N$5000,A10,'Master SKU Catalogue'!$Q$5:$Q$5000,"<0")
A11: Medical devices | B11: =COUNTIFS('Master SKU Catalogue'!$N$5:$N$5000,A11,'Master SKU Catalogue'!$Q$5:$Q$5000,">=-1000") | C11: =IFERROR(ROUND(AVERAGEIFS('Master SKU Catalogue'!$Q$5:$Q$5000,'Master SKU Catalogue'!$N$5:$N$5000,A11),1),"n/a") | D11: =IFERROR(_xlfn.MAXIFS('Master SKU Catalogue'!$Q$5:$Q$5000,'Master SKU Catalogue'!$N$5:$N$5000,A11),"n/a") | E11: =COUNTIFS('Master SKU Catalogue'!$N$5:$N$5000,A11,'Master SKU Catalogue'!$Q$5:$Q$5000,"<0")
A12: Ayurveda | B12: =COUNTIFS('Master SKU Catalogue'!$N$5:$N$5000,A12,'Master SKU Catalogue'!$Q$5:$Q$5000,">=-1000") | C12: =IFERROR(ROUND(AVERAGEIFS('Master SKU Catalogue'!$Q$5:$Q$5000,'Master SKU Catalogue'!$N$5:$N$5000,A12),1),"n/a") | D12: =IFERROR(_xlfn.MAXIFS('Master SKU Catalogue'!$Q$5:$Q$5000,'Master SKU Catalogue'!$N$5:$N$5000,A12),"n/a") | E12: =COUNTIFS('Master SKU Catalogue'!$N$5:$N$5000,A12,'Master SKU Catalogue'!$Q$5:$Q$5000,"<0")
A13: Other | B13: =COUNTIFS('Master SKU Catalogue'!$N$5:$N$5000,A13,'Master SKU Catalogue'!$Q$5:$Q$5000,">=-1000") | C13: =IFERROR(ROUND(AVERAGEIFS('Master SKU Catalogue'!$Q$5:$Q$5000,'Master SKU Catalogue'!$N$5:$N$5000,A13),1),"n/a") | D13: =IFERROR(_xlfn.MAXIFS('Master SKU Catalogue'!$Q$5:$Q$5000,'Master SKU Catalogue'!$N$5:$N$5000,A13),"n/a") | E13: =COUNTIFS('Master SKU Catalogue'!$N$5:$N$5000,A13,'Master SKU Catalogue'!$Q$5:$Q$5000,"<0")

Sheet Delivery ETA
A1: Delivery ETA
A2: Exact text as displayed. Slots: morning 8–10, afternoon 12–2, evening 6–8, night 9–11 (IST). A promise is not a measured delivery time.
A4: Obs ID | B4: Date | C4: Time (IST) | D4: Slot | E4: ETA text (exact) | F4: Where shown | G4: Address PIN | H4: Express option | I4: Scheduled option | J4: Screenshot | K4: Notes
A5: ETA-0 | B5: 2026-10-12 | E5: 15 minutes (claimed) | F5: structured data / FAQ | K5: Marketing claim, not a displayed checkout ETA

Sheet Checkout Fee Matrix
A1: Checkout Fee Matrix
A2: Fill from cart/checkout screens (stop before payment).
A4: Fee | B4: Seen? | C4: Amount / rule (exact text) | D4: Condition (basket value, time) | E4: Basket ID | F4: Screenshot | G4: Notes
A5: Delivery fee
A6: Handling fee
A7: Platform fee
A8: Packaging fee
A9: Small-cart fee
A10: Surge / late-night fee
A11: Priority fee
A12: Rx processing fee
A13: COD fee
A14: Payment fee
A15: Free-delivery threshold
A16: Taxes shown

Sheet Basket Experiments
A1: Basket Experiments
A2: Build each basket in the cart only; never pay or place the order. Total check = 0 means the arithmetic matches.
A4: Basket ID | B4: Target ₹ | C4: Items (name × qty) | D4: Basket MRP ₹ | E4: Selling subtotal ₹ | F4: Product discount ₹ | G4: Coupon ₹ | H4: Delivery ₹ | I4: Handling ₹ | J4: Platform ₹ | K4: Other ₹ | L4: Total payable (shown) ₹ | M4: Computed total ₹ | N4: Total check ₹ | O4: Fees % of subtotal | P4: ETA text | Q4: Free delivery? | R4: Mix | S4: Observed at | T4: Screenshot
A5: B01 | B5: 99 | M5: =IF(ISNUMBER(E5),E5-N(G5)+N(H5)+N(I5)+N(J5)+N(K5),"") | N5: =IF(AND(ISNUMBER(L5),ISNUMBER(M5)),ROUND(L5-M5,2),"") | O5: =IF(AND(ISNUMBER(E5),E5>0),ROUND((N(H5)+N(I5)+N(J5)+N(K5))/E5*100,1),"")
A6: B02 | B6: 199 | M6: =IF(ISNUMBER(E6),E6-N(G6)+N(H6)+N(I6)+N(J6)+N(K6),"") | N6: =IF(AND(ISNUMBER(L6),ISNUMBER(M6)),ROUND(L6-M6,2),"") | O6: =IF(AND(ISNUMBER(E6),E6>0),ROUND((N(H6)+N(I6)+N(J6)+N(K6))/E6*100,1),"")
A7: B03 | B7: 299 | M7: =IF(ISNUMBER(E7),E7-N(G7)+N(H7)+N(I7)+N(J7)+N(K7),"") | N7: =IF(AND(ISNUMBER(L7),ISNUMBER(M7)),ROUND(L7-M7,2),"") | O7: =IF(AND(ISNUMBER(E7),E7>0),ROUND((N(H7)+N(I7)+N(J7)+N(K7))/E7*100,1),"")
A8: B04 | B8: 399 | M8: =IF(ISNUMBER(E8),E8-N(G8)+N(H8)+N(I8)+N(J8)+N(K8),"") | N8: =IF(AND(ISNUMBER(L8),ISNUMBER(M8)),ROUND(L8-M8,2),"") | O8: =IF(AND(ISNUMBER(E8),E8>0),ROUND((N(H8)+N(I8)+N(J8)+N(K8))/E8*100,1),"")
A9: B05 | B9: 499 | M9: =IF(ISNUMBER(E9),E9-N(G9)+N(H9)+N(I9)+N(J9)+N(K9),"") | N9: =IF(AND(ISNUMBER(L9),ISNUMBER(M9)),ROUND(L9-M9,2),"") | O9: =IF(AND(ISNUMBER(E9),E9>0),ROUND((N(H9)+N(I9)+N(J9)+N(K9))/E9*100,1),"")
A10: B06 | B10: 599 | M10: =IF(ISNUMBER(E10),E10-N(G10)+N(H10)+N(I10)+N(J10)+N(K10),"") | N10: =IF(AND(ISNUMBER(L10),ISNUMBER(M10)),ROUND(L10-M10,2),"") | O10: =IF(AND(ISNUMBER(E10),E10>0),ROUND((N(H10)+N(I10)+N(J10)+N(K10))/E10*100,1),"")
A11: B07 | B11: 699 | M11: =IF(ISNUMBER(E11),E11-N(G11)+N(H11)+N(I11)+N(J11)+N(K11),"") | N11: =IF(AND(ISNUMBER(L11),ISNUMBER(M11)),ROUND(L11-M11,2),"") | O11: =IF(AND(ISNUMBER(E11),E11>0),ROUND((N(H11)+N(I11)+N(J11)+N(K11))/E11*100,1),"")
A12: B08 | B12: 799 | M12: =IF(ISNUMBER(E12),E12-N(G12)+N(H12)+N(I12)+N(J12)+N(K12),"") | N12: =IF(AND(ISNUMBER(L12),ISNUMBER(M12)),ROUND(L12-M12,2),"") | O12: =IF(AND(ISNUMBER(E12),E12>0),ROUND((N(H12)+N(I12)+N(J12)+N(K12))/E12*100,1),"")
A13: B09 | B13: 999 | M13: =IF(ISNUMBER(E13),E13-N(G13)+N(H13)+N(I13)+N(J13)+N(K13),"") | N13: =IF(AND(ISNUMBER(L13),ISNUMBER(M13)),ROUND(L13-M13,2),"") | O13: =IF(AND(ISNUMBER(E13),E13>0),ROUND((N(H13)+N(I13)+N(J13)+N(K13))/E13*100,1),"")
A14: B10 | B14: 1499 | M14: =IF(ISNUMBER(E14),E14-N(G14)+N(H14)+N(I14)+N(J14)+N(K14),"") | N14: =IF(AND(ISNUMBER(L14),ISNUMBER(M14)),ROUND(L14-M14,2),"") | O14: =IF(AND(ISNUMBER(E14),E14>0),ROUND((N(H14)+N(I14)+N(J14)+N(K14))/E14*100,1),"")
A15: B11 | B15: 1999 | M15: =IF(ISNUMBER(E15),E15-N(G15)+N(H15)+N(I15)+N(J15)+N(K15),"") | N15: =IF(AND(ISNUMBER(L15),ISNUMBER(M15)),ROUND(L15-M15,2),"") | O15: =IF(AND(ISNUMBER(E15),E15>0),ROUND((N(H15)+N(I15)+N(J15)+N(K15))/E15*100,1),"")
A16: B12 | B16: 2999 | M16: =IF(ISNUMBER(E16),E16-N(G16)+N(H16)+N(I16)+N(J16)+N(K16),"") | N16: =IF(AND(ISNUMBER(L16),ISNUMBER(M16)),ROUND(L16-M16,2),"") | O16: =IF(AND(ISNUMBER(E16),E16>0),ROUND((N(H16)+N(I16)+N(J16)+N(K16))/E16*100,1),"")
M17: =IF(ISNUMBER(E17),E17-N(G17)+N(H17)+N(I17)+N(J17)+N(K17),"") | N17: =IF(AND(ISNUMBER(L17),ISNUMBER(M17)),ROUND(L17-M17,2),"") | O17: =IF(AND(ISNUMBER(E17),E17>0),ROUND((N(H17)+N(I17)+N(J17)+N(K17))/E17*100,1),"")
M18: =IF(ISNUMBER(E18),E18-N(G18)+N(H18)+N(I18)+N(J18)+N(K18),"") | N18: =IF(AND(ISNUMBER(L18),ISNUMBER(M18)),ROUND(L18-M18,2),"") | O18: =IF(AND(ISNUMBER(E18),E18>0),ROUND((N(H18)+N(I18)+N(J18)+N(K18))/E18*100,1),"")
M19: =IF(ISNUMBER(E19),E19-N(G19)+N(H19)+N(I19)+N(J19)+N(K19),"") | N19: =IF(AND(ISNUMBER(L19),ISNUMBER(M19)),ROUND(L19-M19,2),"") | O19: =IF(AND(ISNUMBER(E19),E19>0),ROUND((N(H19)+N(I19)+N(J19)+N(K19))/E19*100,1),"")
M20: =IF(ISNUMBER(E20),E20-N(G20)+N(H20)+N(I20)+N(J20)+N(K20),"") | N20: =IF(AND(ISNUMBER(L20),ISNUMBER(M20)),ROUND(L20-M20,2),"") | O20: =IF(AND(ISNUMBER(E20),E20>0),ROUND((N(H20)+N(I20)+N(J20)+N(K20))/E20*100,1),"")
M21: =IF(ISNUMBER(E21),E21-N(G21)+N(H21)+N(I21)+N(J21)+N(K21),"") | N21: =IF(AND(ISNUMBER(L21),ISNUMBER(M21)),ROUND(L21-M21,2),"") | O21: =IF(AND(ISNUMBER(E21),E21>0),ROUND((N(H21)+N(I21)+N(J21)+N(K21))/E21*100,1),"")
M22: =IF(ISNUMBER(E22),E22-N(G22)+N(H22)+N(I22)+N(J22)+N(K22),"") | N22: =IF(AND(ISNUMBER(L22),ISNUMBER(M22)),ROUND(L22-M22,2),"") | O22: =IF(AND(ISNUMBER(E22),E22>0),ROUND((N(H22)+N(I22)+N(J22)+N(K22))/E22*100,1),"")
M23: =IF(ISNUMBER(E23),E23-N(G23)+N(H23)+N(I23)+N(J23)+N(K23),"") | N23: =IF(AND(ISNUMBER(L23),ISNUMBER(M23)),ROUND(L23-M23,2),"") | O23: =IF(AND(ISNUMBER(E23),E23>0),ROUND((N(H23)+N(I23)+N(J23)+N(K23))/E23*100,1),"")
M24: =IF(ISNUMBER(E24),E24-N(G24)+N(H24)+N(I24)+N(J24)+N(K24),"") | N24: =IF(AND(ISNUMBER(L24),ISNUMBER(M24)),ROUND(L24-M24,2),"") | O24: =IF(AND(ISNUMBER(E24),E24>0),ROUND((N(H24)+N(I24)+N(J24)+N(K24))/E24*100,1),"")
M25: =IF(ISNUMBER(E25),E25-N(G25)+N(H25)+N(I25)+N(J25)+N(K25),"") | N25: =IF(AND(ISNUMBER(L25),ISNUMBER(M25)),ROUND(L25-M25,2),"") | O25: =IF(AND(ISNUMBER(E25),E25>0),ROUND((N(H25)+N(I25)+N(J25)+N(K25))/E25*100,1),"")
M26: =IF(ISNUMBER(E26),E26-N(G26)+N(H26)+N(I26)+N(J26)+N(K26),"") | N26: =IF(AND(ISNUMBER(L26),ISNUMBER(M26)),ROUND(L26-M26,2),"") | O26: =IF(AND(ISNUMBER(E26),E26>0),ROUND((N(H26)+N(I26)+N(J26)+N(K26))/E26*100,1),"")
M27: =IF(ISNUMBER(E27),E27-N(G27)+N(H27)+N(I27)+N(J27)+N(K27),"") | N27: =IF(AND(ISNUMBER(L27),ISNUMBER(M27)),ROUND(L27-M27,2),"") | O27: =IF(AND(ISNUMBER(E27),E27>0),ROUND((N(H27)+N(I27)+N(J27)+N(K27))/E27*100,1),"")
M28: =IF(ISNUMBER(E28),E28-N(G28)+N(H28)+N(I28)+N(J28)+N(K28),"") | N28: =IF(AND(ISNUMBER(L28),ISNUMBER(M28)),ROUND(L28-M28,2),"") | O28: =IF(AND(ISNUMBER(E28),E28>0),ROUND((N(H28)+N(I28)+N(J28)+N(K28))/E28*100,1),"")
... M100: =IF(ISNUMBER(E100),E100-N(G100)+N(H100)+N(I100)+N(J100)+N(K100),"") | N100: =IF(AND(ISNUMBER(L100),ISNUMBER(M100)),ROUND(L100-M100,2),"") | O100: =IF(AND(ISNUMBER(E100),E100>0),ROUND((N(H100)+N(I100)+N(J100)+N(K100))/E100*100,1),"")

Sheet Promotions
A1: Promotions
A2: Offers visible to an ordinary customer.
A4: Promo | B4: Type | C4: Code (if public) | D4: Discount rule | E4: Min basket ₹ | F4: Cap ₹ | G4: Category | H4: Validity | I4: Where seen | J4: Observed at | K4: Screenshot
A5: Discounts, cashback, coupons | B5: claimed | D5: "Download the app to get the best deals" (FAQ) | I5: FAQ | J5: 2026-10-12

Sheet Search Tests
A1: Search Tests
A2: Type the query in the site/app search at the fixed address. Results are not medical advice.
A4: Query type | B4: Query | C4: Results (count) | D4: Exact match position | E4: Top 5 results | F4: Autocomplete / suggestions | G4: Typo handled? | H4: Out-of-stock shown? | I4: Alternatives offered | J4: Filters / sort | K4: Observed at | L4: Screenshot
A5: brand | B5: Dolo 650
A6: brand | B6: Pan 40
A7: brand | B7: Crocin Advance
A8: generic | B8: paracetamol
A9: salt | B9: pantoprazole 40
A10: salt | B10: metformin 500
A11: typo | B11: paracetmol
A12: typo | B12: azithromicin
A13: no-space | B13: dolo650
A14: partial | B14: thyro
A15: symptom | B15: fever
A16: symptom | B16: acidity
... A24: Hindi | B24: bukhar ki dawai

Sheet Prescription Workflows
A1: Prescription Workflows
A2: Never upload a real prescription or patient data. Status: observed / claimed / not_found / untestable.
A4: Feature | B4: Status | C4: What is shown (exact) | D4: Source | E4: Observed at | F4: Screenshot
A5: Prescription upload | B5: claimed | C5: Upload prescription on the app (FAQ, HowTo) | D5: https://plazza.in (schema.org JSON-LD in page HTML) | E5: 2026-10-12
A6: Multiple prescriptions
A7: Multi-medicine order
A8: Pharmacist review messaging
A9: Rx-to-cart conversion
A10: Substitution consent
A11: Unavailable medicine handling
A12: Partial fulfilment
A13: Split deliveries
A14: Refill reminders
A15: Repeat orders
A16: Family profiles
A17: Saved prescriptions | B17: claimed | C17: /saved-prescriptions page listed in sitemap | D17: https://plazza.in/sitemap.xml | E17: 2026-10-12
A18: WhatsApp ordering

Sheet Membership and Loyalty
A1: Membership and Loyalty
A2: Pinzzo benchmark column is our plan, not a competitor fact.
A4: Feature | B4: Status | C4: Plazza (exact) | D4: Pinzzo benchmark | E4: Source | F4: Observed at
A5: Membership plan
A6: Price | D6: ₹149 / 90 days
A7: Duration
A8: Free delivery
A9: Fee waivers
A10: Extra discount
A11: Family cover
A12: Renewal / cancellation terms
A13: Referral credit
A14: Loyalty points
A15: Wallet / cashback | B15: claimed | C15: "cashback offers" (FAQ) | E15: https://plazza.in (schema.org JSON-LD in page HTML) | F15: 2026-10-12

Sheet WhatsApp and Ordering Channels
A1: WhatsApp and Ordering Channels
A2: Public entry points only; no automated or bulk messaging.
A4: Channel | B4: Status | C4: Entry point | D4: What it offers | E4: Hours | F4: Source | G4: Observed at
A5: Website | B5: observed | C5: https://plazza.in | D5: Catalogue, cart (client-side) | E5: 24/7 claimed | F5: https://plazza.in (schema.org JSON-LD in page HTML) | G5: 2026-10-12
A6: Android app | B6: observed | C6: https://play.google.com/store/apps/details?id=com.plazza.app | F6: https://plazza.in (schema.org JSON-LD in page HTML) | G6: 2026-10-12
A7: iOS app | B7: observed | C7: https://apps.apple.com/in/app/plazza-medicines-in-minutes/id6738200177 | F7: https://plazza.in (schema.org JSON-LD in page HTML) | G7: 2026-10-12
A8: Email | B8: claimed | C8: support@plazza.in; founders@plazza.in | F8: https://plazza.in (schema.org JSON-LD in page HTML) | G8: 2026-10-12
A9: Phone | B9: not_found | C9: Structured data shows a placeholder "+91-XXXXX-XXXXX" | F9: https://plazza.in (schema.org JSON-LD in page HTML) | G9: 2026-10-12
A10: WhatsApp | B10: pending
A11: Instagram / LinkedIn | B11: observed | C11: instagram.com/plazza.in; linkedin.com/company/plazza-club | F11: https://plazza.in (schema.org JSON-LD in page HTML) | G11: 2026-10-12

Sheet Serviceability
A1: Serviceability
A2: Use ONE fixed Bengaluru address for the whole study. Do not bypass location checks.
A4: Field | B4: Value | C4: Kind | D4: Source | E4: Observed at
A5: Fixed study address | B5: [choose a Bengaluru address, e.g. near Bellandur 560103] | C5: input
A6: Serviceable at study address?
A7: Location selection mechanism
A8: Claimed service area | B8: Bengaluru | C8: claimed | D8: https://plazza.in (schema.org JSON-LD in page HTML) | E8: 2026-10-12
A9: Plazza office coordinates | B9: 12.9327764, 77.6834966 (Bellandur) | C9: claimed | D9: https://plazza.in (schema.org JSON-LD in page HTML) | E9: 2026-10-12
A10: Operating hours | B10: 24/7 | C10: claimed | D10: https://plazza.in (schema.org JSON-LD in page HTML) | E10: 2026-10-12
A11: Overlap with Pinzzo (Gurugram) | B11: None observed: Plazza claims Bengaluru only | C11: observed | D11: https://plazza.in (schema.org JSON-LD in page HTML) | E11: 2026-10-12

Sheet Customer Experience
A1: Customer Experience
A2: Journey to the last screen before payment. Never place an order.
A4: Step | B4: Required? | C4: What happens (exact) | D4: Friction / blockers | E4: Time taken (s) | F4: Screenshot
A5: Landing
A6: Location selection
A7: Login (OTP)
A8: Search / browse
A9: Product page
A10: Add to cart
A11: Cart
A12: Address
A13: Prescription step
A14: Coupon
A15: Checkout summary (stop here)

Sheet Policies and Compliance
A1: Policies and Compliance
A2: Record source URL and date for each item.
A4: Item | B4: Value / summary | C4: Status | D4: Source | E4: Observed at
A5: Legal entity | B5: PLAZZA HEALTH PRIVATE LIMITED | C5: claimed | D5: https://plazza.in (schema.org JSON-LD in page HTML) | E5: 2026-10-12
A6: Address | B6: Bellandur, Bengaluru 560103 | C6: claimed | D6: https://plazza.in (schema.org JSON-LD in page HTML) | E6: 2026-10-12
A7: Drug licence number | C7: pending | D7: not found in page HTML | E7: 2026-10-12
A8: Terms | B8: Text loads client-side; capture manually | C8: pending | D8: https://plazza.in/terms | E8: 2026-10-12
A9: Privacy policy | B9: Text loads client-side; capture manually | C9: pending | D9: https://plazza.in/privacy-policy | E9: 2026-10-12
A10: Cancellation & refund | B10: Text loads client-side; capture manually | C10: pending | D10: https://plazza.in/cancellation-refund | E10: 2026-10-12
A11: Grievance officer | C11: pending | E11: 2026-10-12
A12: Medicines genuine / licensed claim | B12: "licensed pharmacy", "100% genuine" (FAQ) | C12: claimed | D12: https://plazza.in (schema.org JSON-LD in page HTML) | E12: 2026-10-12

Sheet Change Detection
A1: Change Detection
A2: One row per repeat observation of the same product. A single snapshot is not a trend.
A4: Snapshot ID | B4: Observed at | C4: Address PIN | D4: Product (Obs ID) | E4: MRP ₹ | F4: Selling ₹ | G4: Availability | H4: ETA text | I4: Fees text | J4: Promo | K4: Changed vs previous? | L4: Notes

Sheet Pinzzo Comparison
A1: Pinzzo Comparison
A2: Competitor column = observed or claimed facts only. Opportunity is our analysis.
A4: Dimension | B4: Plazza observed / claimed | C4: Pinzzo benchmark | D4: Opportunity
A5: Delivery ETA | B5: 15 min (claimed) | C5: 30–40 min
A6: Operating hours | B6: 24/7 (claimed) | C6: TBD
A7: Assortment | B7: 20,000–100,000+ (claims conflict) | C7: Medicine-first, localised
A8: SKU availability | B8: pending manual sample | C8: Localisation-led
A9: Minimum order | B9: None (claimed) | C9: TBD
A10: Delivery fees | B10: ₹0 in Offer data; checkout fees pending | C10: ₹25 under ₹499; ₹5 handling; ₹15 night
A11: Discounts | B11: Coupons/cashback claimed; depth pending | C11: 10% model assumption
A12: Membership | B12: pending | C12: ₹149 / 90 days
A13: Prescription ordering | B13: Upload in app (claimed); saved prescriptions page exists | C13: Multi-prescription
A14: WhatsApp ordering | B14: pending | C14: Planned
A15: Split shipments | B15: pending | C15: Avoid
A16: Geography | B16: Bengaluru | C16: Gurugram (no overlap today)
A17: Customer retention | B17: Public evidence only: app 4.1 from 31 ratings (their page) | C17: Refill-led

Sheet Data Quality and Limitations
A1: Data Quality and Limitations
A2: Register of every constraint and exclusion.
A4: Area | B4: Status | C4: Detail
A5: Automated product, price and stock collection | B5: Not performed | C5: Product data loads only from /api/, which plazza.in/robots.txt disallows for all crawlers. Collected manually instead.
A6: Policy pages | B6: Manual only | C6: Terms, privacy and refund text is rendered client-side from the same API.
A7: Assortment claims | B7: Conflicting | C7: Page structured data says 20,000+, 35,000+ and 100,000+ in different blocks.
A8: Structured data freshness | B8: Stale fields | C8: priceValidUntil 2025-12-31; phone is a placeholder.
A9: App rating | B9: Unverified | C9: 4.1 / 31 ratings is Plazza's own markup, not checked on the stores.
A10: Geography | B10: Different market | C10: Plazza claims Bengaluru only; findings benchmark the model, not Gurugram prices.
A11: Inventory quantities | B11: Out of scope | C11: Not inferred from add-to-cart or any probing.
A12: Orders, payments, real prescriptions | B12: Out of scope | C12: No orders placed, no payments, no medical documents uploaded.
